FoldLayer/__init__.py
FoldLayer/fold.py
FoldLayer/soft_fold.py
FoldLayer-0.1.0.dist-info/LICENSE
FoldLayer-0.1.0.dist-info/METADATA
FoldLayer-0.1.0.dist-info/WHEEL
FoldLayer-0.1.0.dist-info/top_level.txt
FoldLayer-0.1.0.dist-info/RECORD
