Metadata-Version: 2.2
Name: FoldLayer
Version: 0.1.0
Summary: A package for fold layers in neural networks
Home-page: https://github.com/binDebug3/FoldLayer
Author: Dallin Stewart, Sam Layton, Jeddy Bennett, Nathaniel Driggs
Author-email: dallinpstewart@gmail.com
Classifier: Programming Language :: Python :: 3
Classifier: License :: OSI Approved :: MIT License
Classifier: Operating System :: OS Independent
Requires-Python: >=3.6
License-File: LICENSE
Requires-Dist: torch
Dynamic: author
Dynamic: author-email
Dynamic: classifier
Dynamic: description
Dynamic: description-content-type
Dynamic: home-page
Dynamic: requires-dist
Dynamic: requires-python
Dynamic: summary
